src/fixed_mult.v
module z_fixed_mult(
    input clk,
    input [size-1:0] in0,
    input [size-1:0] in1,
    output reg [size-1:0] product
);
    parameter size = 32;
    reg [(size*2) - 1: 0] interm;

    assign interm = {{32{in0[31]}}, in0} * {{32{in1[31]}},in1};

    always @(posedge clk) begin
        product <= interm[2*size-1-(size/2):(size/2)];
    end


    initial begin
        $dumpfile("dump.vcd");
        $dumpvars(3, z_fixed_mult);
    end

endmodule

module fixed_mult(
    input [size-1:0] in0,
    input [size-1:0] in1,
    output [size-1:0] product
);
    parameter size = 32;
    reg [(size*2) - 1: 0] interm;

    assign interm = {{32{in0[31]}}, in0} * {{32{in1[31]}},in1};
    assign product = interm[2*size-1-(size/2):(size/2)];


    initial begin
        $dumpfile("dump.vcd");
        $dumpvars(3, fixed_mult);
    end

endmodule

src/MAC.v
module mac(
    input [size-1:0] in0,
    input [size-1:0] in1,
    input [size-1:0] cons,
    input [size-1:0] in3,
    output reg [size-1:0] d
);
    parameter size = 32;

    wire [size-1:0] in;
    wire [size-1:0] temp;
    wire [size-1:0] mult;
    wire [size-1:0] sum0;

    assign sum0 = in0 + in1;

    fixed_mult m0(.in0(sum0), .in1(cons), .product(mult));

    //assign in = a + b;
    //assign temp = in * const;


    //assign d = ((in0+in1)*cons) + in3;
    assign d = mult + in3;

    initial begin
        $dumpfile("dump.vcd");
        $dumpvars(2, mac);
    end

endmodule

src/transform.v
//Implementation of a one-dimensional recursive 9/7 DWT architecture

module transform (
    input clk,
    input resetn,
    input [size-1:0] x,
    output reg [size-1:0] L,
    output reg [size-1:0] H
    //Add register and delay unit enables to signal IO list
);

    //enable signals
    //reg EnR4;
    reg EnR3;
    reg EnR2;
    reg EnR1;
    reg EnD1a;
    reg EnD2a;
    reg EnD3a;
    //reg EnD4a;
    reg EnD1b;
    reg EnD2b;
    reg EnD3b;
    //reg EnD4b;
    reg EnD1c;
    reg EnD2c;
    reg EnD3c;
    //reg EnD4c;
    reg EnD1d;
    reg EnD2d;
    reg EnD3d;
    //reg EnD4d;
    reg EnR2p;
    reg EnR3p;
    //reg EnR4p;

    //Control switch signals
    reg [1:0] S1;
    reg [1:0] S2;
    reg [1:0] S3;
    reg [1:0] S4;
    reg [1:0] S5;
    reg [1:0] S6;
    reg S7;

    parameter size = 32;

    parameter alpha = 2*(2**16);
    parameter beta = 3*(2**16);
    parameter gamma = 4*(2**16);
    parameter delta = 5*(2**16);
    parameter zeta = 6*(2**16);
    parameter omega = 2;
    parameter nabla = 2;

    //Enable signals

    //Even registers
    reg [size-1:0] R1;
    reg [size-1:0] R2;
    reg [size-1:0] R3;
    //reg [size-1:0] R4;

    //Odd registers
    reg [size-1:0] R2p;
    reg [size-1:0] R3p;
    //reg [size-1:0] R4p;

    //Delay units
    reg [size-1:0] D1a;
    reg [size-1:0] D2a;
    reg [size-1:0] D3a;
    //reg [size-1:0] D4a;

    reg [size-1:0] D1b;
    reg [size-1:0] D2b;
    reg [size-1:0] D3b;
    //reg [size-1:0] D4b;

    reg [size-1:0] D1c;
    reg [size-1:0] D2c;
    reg [size-1:0] D3c;
    //reg [size-1:0] D4c;

    reg [size-1:0] D1d;
    reg [size-1:0] D2d;
    reg [size-1:0] D3d;
    //reg [size-1:0] D4d;

    //shift registers
    reg [3:0] EnD1shift;
    reg [3:0] EnD2shift;
    reg [3:0] EnD3shift;
    reg [3:0] S3shift;

    reg [size-1: 0] Even0;
    reg [size-1: 0] Even1;
    reg [size-1: 0] Even2;
    reg [size-1: 0] Even3;
    reg [size-1: 0] Even4;
    reg [size-1: 0] Even5;

    reg [size-1: 0] Odd0;
    reg [size-1: 0] Odd1;
    reg [size-1: 0] Odd2;
    reg [size-1: 0] Odd3;
    reg [size-1: 0] Odd4;
    reg [size-1: 0] Odd5;

    //feedback unit
    reg [size-1:0] y;
    //reg [size-1:0] L;

    //Just for Daub4
    assign EnD1a = EnD1shift[2];
    assign EnD2a = EnD2shift[2];
    assign EnD3a = EnD3shift[2];
    assign S3 = S3shift[3:2];

    always@(*) begin
        //Muxes
        //assign Even0 = S1[1] ? (S1[0] ? /*R4*/1'b0 : R3) : (S1[0] ? R2 : R1);
        //assign Even1 = S3[1] ? (S3[0] ? /*D4a*/1'b0 : D3a) : (S3[0] ? D2a : D1a);
        //assign Even3 = S5[1] ? (S5[0] ? /*D4c*/1'b0 : D3c) : (S5[0] ? D2c : D1c);
        
        //assign Odd0 = S2[1] ? (S2[0] ? /*R4p*/1'b0 : R3p) : (S2[0] ? R2p : x);
        //assign Odd2 = S4[1] ? (S4[0] ? /*D4b*/1'b0 : D3b) : (S4[0] ? D2b : D1b);
        //assign Odd4 = S6[1] ? (S6[0] ? /*D4d*/1'b0 : D3d) : (S6[0] ? D2d : D1d);

        //if (S7) y <= Even5;
        //else L <= Even5;

        //DAUB-4 DWT Muxes
        assign Even0 = S1[1] ? (S1[0] ? /*R4*/R3 : R2) : (S1[0] ? R1 : 1'b0);
        assign Odd0 = S2[1] ? (S2[0] ? /*R4p*/R3p : y) : (S2[0] ? x : 1'b0);

        assign Odd2 = S3[1] ? (S3[0] ? /*D4a*/D3a : D2a) : (S3[0] ? D1a : 1'b0);

        if (S4) y<= Even3;
        else L<= Even3;


    end

    always@(posedge clk) begin
        if (EnR1) R1 <= x;
        if (EnR2) R2 <= y;
        if (EnR3) R3 <= y;
        //if (EnR4) R4 <= y;

        //if (EnR2p) R2p <= y;
        R2p <= y;
        if (EnR3p) R3p <= y;
        //if (EnR4p) R4p <= y;

        //if (EnD1a) D1a <= Even0;
        //if (EnD2a) D2a <= Even0;
        //if (EnD3a) D3a <= Even0;
        //if (EnD4a) D4a <= Even0;

        if (EnD1a) D1a <= Odd1;
        if (EnD2a) D2a <= Odd1;
        if (EnD3a) D3a <= Odd1;
        //if (EnD4a) D4a <= Odd1;

        //if (EnD1b) D1a <= Odd1;
        //if (EnD2b) D2a <= Odd1;
        //if (EnD3b) D3a <= Odd1;
        //if (EnD4b) D4a <= Odd1;

        //if (EnD1c) D1c <= Even2;
        //if (EnD2c) D2c <= Even2;
        //if (EnD3c) D3c <= Even2;
        //if (EnD4c) D4c <= Even2;

        //if (EnD1d) D1d <= Odd3;
        //if (EnD2d) D2d <= Odd3;
        //if (EnD3d) D3d <= Odd3;
        //if (EnD4d) D4d <= Odd3;
        
    end

    //Multiple and Accumulate units
    //mac u0(.in0(Even0), .in1(Even1), .in3(Odd0), .d(Odd1), .cons(alpha));
    //mac u1(.in0(Odd1), .in1(Odd2), .in3(Even1), .d(Even2), .cons(beta));
    //mac u2(.in0(Even2), .in1(Even3), .in3(Odd2), .d(Odd3), .cons(gamma));
    //mac u3(.in0(Odd3), .in1(Odd4), .in3(Even3), .d(Even4), .cons(delta));

    //Multiply and accumulate units for Daub-4 DWT
    mac u0(.in0(Even0), .in1(0), .in3(Odd0), .d(Odd1), .cons(alpha));
    mac u1(.in0(Odd1), .in1(0), .in3(Even0), .d(Even1), .cons(beta));
    mac u2(.in0(Odd2), .in1(0), .in3(Even1), .d(Even2), .cons(gamma));
    mac u3(.in0(Even2), .in1(0), .in3(Odd2), .d(Odd3), .cons(1));

    fixed_mult m1(.in0(Even2), .in1(omega), .product(Even3));
    fixed_mult m2(.in0(Odd3), .in1(nabla), .product(H));

    //control unit
    reg [3:0] state;
    reg [2:0] cycle1;
    reg [1:0] cycle2;
    reg cycle2En;
    reg finalEn;
    reg SEn;
    reg DshiftEn;

    reg preEnD1a;
    reg preEnD2a;
    reg preEnD3a;

    reg [1:0] preS3;

    //enable signals, might need to extend the range for switch logic
    always@(*) begin
        EnR1 = 1'b0;
        EnR2 = 1'b0;
        EnR3 = 1'b0;
        EnR2p = 1'b0;
        EnR3p = 1'b0;
        //S1 = 2'b0;
        //S2 = 2'b0;
        //S3 = 2'b0;
        //S4 = 2'b0;
        //S5 = 2'b0;
        //S6 = 2'b0;
        //S7 = 1'b0;
        SEn = 1'b0;
        preEnD1a = 1'b0;
        preEnD2a = 1'b0;
        preEnD3a = 1'b0;
        //preS3 = 2'b0;
        //EnD1a = 1'b0;

        if (!cycle1[0]) begin //checking 2k cycle
            EnR1 = 1'b1;
            preEnD1a = 1'b1;
        end

        if (cycle1[0]) begin//checking 2k+1 cycle
            S1 = 2'b01;
            S2 = 2'b01;
            preS3 = 2'b01;
        end

        if (cycle1[1] & !cycle1[0]) begin //4k+4 cycle
            EnR2 = 1'b1; 
            EnR2p = 1'b1; 
            preEnD2a = 1'b1;
        end

        if ((cycle2[0] & !cycle2[1])) begin  //4k+6 cycle
            S1 = 2'b10;
            S2 = 2'b10;
            preS3 = 2'b10;
        end

        if ((!cycle1[2] & !cycle1[1] & !cycle1[0]) & (state[3] & (state[0]))) begin //8k+9 cycle
            EnR3 = 1'b1;
            EnR3p = 1'b1;
            preEnD3a = 1'b1;
        end

        if ((state[0] & state[1] & state[2] & state[3]) & (cycle1[2] & cycle1[1] & cycle1[0])) begin //8k+16 cycle
            S1 = 2'b11;
            S2 = 2'b11;
            preS3 = 2'b11;
        end

        

    end

    //counter
    always@(posedge clk) begin
        if (!resetn) begin
            state <= 0;
            cycle1 <= 0;
            cycle2 <= 0;
            cycle2En <= 0;
            finalEn <= 0;


        end
        else begin
            if (state == 4'b1111) begin
                state <= 4'b1111; //counts to 25
                finalEn <= 1;
            end
            else state <= state + 1;

            if (cycle1 == 3'b111) cycle1 <= 0;
            else cycle1 <= cycle1 + 1;

            if (state[1] & state[0]) cycle2En <= 1;

            if (cycle2En) cycle2 <= cycle2 + 1;

            S3shift <= {S3shift[1:0], preS3};

            EnD1shift <= {EnD1shift[3:0], preEnD1a};
            EnD2shift <= {EnD2shift[3:0], preEnD2a};
            EnD3shift <= {EnD3shift[3:0], preEnD3a};
        
        end
    end
    

    initial begin
        $dumpfile("dump.vcd");
        $dumpvars(1, transform);
    end


endmodule

verif/dump.vcd
$date
	Tue Oct 22 22:33:47 2024
$end
$version
	Icarus Verilog
$end
$timescale
	1ps
$end
$scope module transform $end
$scope module u0 $end
$scope module m0 $end
$var wire 32 ! in0 [31:0] $end
$var wire 32 " in1 [31:0] $end
$var wire 32 # product [31:0] $end
$var wire 64 $ interm [63:0] $end
$var parameter 32 % size $end
$upscope $end
$upscope $end
$upscope $end
$scope module transform $end
$scope module u0 $end
$var wire 32 & cons [31:0] $end
$var wire 32 ' in0 [31:0] $end
$var wire 32 ( in1 [31:0] $end
$var wire 32 ) in3 [31:0] $end
$var wire 32 * sum0 [31:0] $end
$var wire 32 + mult [31:0] $end
$var wire 32 , d [31:0] $end
$var parameter 32 - size $end
$scope module m0 $end
$upscope $end
$upscope $end
$upscope $end
$scope module transform $end
$scope module u1 $end
$scope module m0 $end
$var wire 32 . in0 [31:0] $end
$var wire 32 / in1 [31:0] $end
$var wire 32 0 product [31:0] $end
$var wire 64 1 interm [63:0] $end
$var parameter 32 2 size $end
$upscope $end
$upscope $end
$upscope $end
$scope module transform $end
$scope module u1 $end
$var wire 32 3 cons [31:0] $end
$var wire 32 4 in0 [31:0] $end
$var wire 32 5 in1 [31:0] $end
$var wire 32 6 in3 [31:0] $end
$var wire 32 7 sum0 [31:0] $end
$var wire 32 8 mult [31:0] $end
$var wire 32 9 d [31:0] $end
$var parameter 32 : size $end
$scope module m0 $end
$upscope $end
$upscope $end
$upscope $end
$scope module transform $end
$scope module u2 $end
$scope module m0 $end
$var wire 32 ; in0 [31:0] $end
$var wire 32 < in1 [31:0] $end
$var wire 32 = product [31:0] $end
$var wire 64 > interm [63:0] $end
$var parameter 32 ? size $end
$upscope $end
$upscope $end
$upscope $end
$scope module transform $end
$scope module u2 $end
$var wire 32 @ cons [31:0] $end
$var wire 32 A in0 [31:0] $end
$var wire 32 B in1 [31:0] $end
$var wire 32 C in3 [31:0] $end
$var wire 32 D sum0 [31:0] $end
$var wire 32 E mult [31:0] $end
$var wire 32 F d [31:0] $end
$var parameter 32 G size $end
$scope module m0 $end
$upscope $end
$upscope $end
$upscope $end
$scope module transform $end
$scope module u3 $end
$scope module m0 $end
$var wire 32 H in0 [31:0] $end
$var wire 32 I in1 [31:0] $end
$var wire 32 J product [31:0] $end
$var wire 64 K interm [63:0] $end
$var parameter 32 L size $end
$upscope $end
$upscope $end
$upscope $end
$scope module transform $end
$scope module u3 $end
$var wire 32 M cons [31:0] $end
$var wire 32 N in0 [31:0] $end
$var wire 32 O in1 [31:0] $end
$var wire 32 P in3 [31:0] $end
$var wire 32 Q sum0 [31:0] $end
$var wire 32 R mult [31:0] $end
$var wire 32 S d [31:0] $end
$var parameter 32 T size $end
$scope module m0 $end
$upscope $end
$upscope $end
$upscope $end
$scope module transform $end
$scope module m1 $end
$var wire 32 U in1 [31:0] $end
$var wire 32 V product [31:0] $end
$var wire 64 W interm [63:0] $end
$var wire 32 X in0 [31:0] $end
$var parameter 32 Y size $end
$upscope $end
$upscope $end
$scope module transform $end
$scope module m2 $end
$var wire 32 Z in1 [31:0] $end
$var wire 32 [ product [31:0] $end
$var wire 64 \ interm [63:0] $end
$var wire 32 ] in0 [31:0] $end
$var parameter 32 ^ size $end
$upscope $end
$upscope $end
$scope module transform $end
$var wire 1 _ clk $end
$var wire 1 ` resetn $end
$var wire 32 a x [31:0] $end
$var wire 2 b S3 [1:0] $end
$var wire 32 c Odd3 [31:0] $end
$var wire 32 d Odd1 [31:0] $end
$var wire 32 e H [31:0] $end
$var wire 32 f Even3 [31:0] $end
$var wire 32 g Even2 [31:0] $end
$var wire 32 h Even1 [31:0] $end
$var wire 1 i EnD3a $end
$var wire 1 j EnD2a $end
$var wire 1 k EnD1a $end
$var parameter 64 l alpha $end
$var parameter 64 m beta $end
$var parameter 64 n delta $end
$var parameter 64 o gamma $end
$var parameter 32 p nabla $end
$var parameter 32 q omega $end
$var parameter 32 r size $end
$var parameter 64 s zeta $end
$var reg 32 t D1a [31:0] $end
$var reg 32 u D2a [31:0] $end
$var reg 32 v D3a [31:0] $end
$var reg 4 w EnD1shift [3:0] $end
$var reg 4 x EnD2shift [3:0] $end
$var reg 4 y EnD3shift [3:0] $end
$var reg 1 z EnR1 $end
$var reg 1 { EnR2 $end
$var reg 1 | EnR2p $end
$var reg 1 } EnR3 $end
$var reg 1 ~ EnR3p $end
$var reg 32 !" Even0 [31:0] $end
$var reg 32 "" L [31:0] $end
$var reg 32 #" Odd0 [31:0] $end
$var reg 32 $" Odd2 [31:0] $end
$var reg 32 %" R1 [31:0] $end
$var reg 32 &" R2 [31:0] $end
$var reg 32 '" R2p [31:0] $end
$var reg 32 (" R3 [31:0] $end
$var reg 32 )" R3p [31:0] $end
$var reg 2 *" S1 [1:0] $end
$var reg 2 +" S2 [1:0] $end
$var reg 4 ," S3shift [3:0] $end
$var reg 2 -" S4 [1:0] $end
$var reg 1 ." SEn $end
$var reg 3 /" cycle1 [2:0] $end
$var reg 2 0" cycle2 [1:0] $end
$var reg 1 1" cycle2En $end
$var reg 1 2" finalEn $end
$var reg 1 3" preEnD1a $end
$var reg 1 4" preEnD2a $end
$var reg 1 5" preEnD3a $end
$var reg 2 6" preS3 [1:0] $end
$var reg 4 7" state [3:0] $end
$var reg 32 8" y [31:0] $end
$upscope $end
$enddefinitions $end
$comment Show the parameter values. $end
$dumpall
b1100000000000000000 s
b100000 r
b10 q
b10 p
b1000000000000000000 o
b1010000000000000000 n
b110000000000000000 m
b100000000000000000 l
b100000 ^
b100000 Y
b100000 T
b100000 L
b100000 G
b100000 ?
b100000 :
b100000 2
b100000 -
b100000 %
$end
#0
$dumpvars
bx 8"
bx 7"
bx 6"
x5"
x4"
x3"
x2"
x1"
bx 0"
bx /"
x."
bx -"
bx ,"
bx +"
bx *"
bx )"
bx ("
bx '"
bx &"
bx %"
bx $"
bx #"
bx ""
bx !"
x~
x}
x|
x{
xz
bx y
bx x
bx w
bx v
bx u
bx t
xk
xj
xi
bx h
bx g
bx f
bx e
bx d
bx c
bx b
bz a
0`
0_
bx ]
bx \
bx [
b10 Z
bx X
bx W
bx V
b10 U
bx S
bx R
bx Q
bx P
b0 O
bx N
b1 M
bx K
bx J
b1 I
bx H
bx F
bx E
bx D
bx C
b0 B
bx A
b1000000000000000000 @
bx >
bx =
b1000000000000000000 <
bx ;
bx 9
bx 8
bx 7
bx 6
b0 5
bx 4
b110000000000000000 3
bx 1
bx 0
b110000000000000000 /
bx .
bx ,
bx +
bx *
bx )
b0 (
bx '
b100000000000000000 &
bx $
bx #
b100000000000000000 "
bx !
$end
#5
b10000000000000000 a
1`
05"
04"
13"
0."
0~
0|
0}
0{
1z
02"
01"
b0 0"
b0 /"
b0 7"
1_
#10
0_
#15
b100000000000000000 a
b11010000000000000000 9
b11010000000000000000 C
b11010000000000000000 h
b11000000000000000000 0
b11000000000000000000 8
b110000000000000000000000000000000000 1
b1000000000000000000 .
b1000000000000000000 7
b1000000000000000000 ,
b1000000000000000000 4
b1000000000000000000 d
b100000000000000000 #
b100000000000000000 +
b100000000000000000 )
b100000000000000000 #"
b1000000000000000000000000000000000 $
b10000000000000000 !
b10000000000000000 *
b10000000000000000 '
b10000000000000000 6
b10000000000000000 !"
b1 6"
b1 +"
b1 *"
03"
0z
bx0 y
bx0 x
bx1 w
b1 /"
b1 7"
b10000000000000000 %"
1_
#20
0_
#25
b100000000000000000000 9
b100000000000000000000 C
b100000000000000000000 h
b11110000000000000000 0
b11110000000000000000 8
b111100000000000000000000000000000000 1
b1010000000000000000 .
b1010000000000000000 7
b1010000000000000000 ,
b1010000000000000000 4
b1010000000000000000 d
b110000000000000000 )
b110000000000000000 #"
b110000000000000000 a
14"
1|
1{
13"
1z
bx00 y
bx00 x
bx10 w
bx01 ,"
b10 /"
b10 7"
1_
#30
0_
#35
b1000000000000000000 )
b1000000000000000000 #"
b1000000000000000000 a
b111100000000000000000 0
b111100000000000000000 8
b1111000000000000000000000000000000000 1
b10100000000000000000 .
b10100000000000000000 7
b10100000000000000000 ,
b10100000000000000000 4
b10100000000000000000 d
b1100000000000000000 #
b1100000000000000000 +
0i
0j
1k
b1 b
04"
03"
0|
0{
0z
b11000000000000000000000000000000000 $
b110000000000000000 !
b110000000000000000 *
b1000010000000000000000 9
b1000010000000000000000 C
b1000010000000000000000 h
b110000000000000000 '
b110000000000000000 6
b110000000000000000 !"
bx000 y
bx001 x
bx101 w
b101 ,"
b11 /"
b11 7"
b110000000000000000 %"
1_
#40
0_
#45
b1001000000000000000000 9
b1001000000000000000000 C
b1001000000000000000000 h
b1000010000000000000000 0
b1000010000000000000000 8
b10000100000000000000000000000000000000 1
b10110000000000000000 .
b10110000000000000000 7
b10110000000000000000 ,
b10110000000000000000 4
b10110000000000000000 d
b1010000000000000000 )
b1010000000000000000 #"
b1010000000000000000 a
b10011000 ""
b10100 [
b10100 e
b101000000000010011000 \
b10100000000001001100 S
b10100000000001001100 ]
b10100000000001001100 c
b1001100 J
b1001100 R
b10011000 V
b10011000 f
b10011000000000000000000 K
b10011000000000000000000 H
b10011000000000000000000 Q
b100110000000000000000000 W
b10011000000000000000000 F
b10011000000000000000000 N
b10011000000000000000000 X
b10011000000000000000000 g
b1010000000000000000000 =
b1010000000000000000000 E
b10100000000000000000000000000000000000 >
b10100000000000000000 ;
b10100000000000000000 D
b10100000000000000000 A
b10100000000000000000 P
b10100000000000000000 $"
0k
13"
1z
b10100000000000000000 t
b0 y
b10 x
b1010 w
11"
b100 /"
b100 7"
1_
#50
0_
#55
b1100000000000000000 a
bx ""
bx [
bx e
bx 0
bx 8
bx )
bx #"
bx 1
bx .
bx 7
bx ,
bx 4
bx d
bx #
bx +
bx \
bx S
bx ]
bx c
bx J
bx R
bx V
bx f
1j
1k
b10 6"
b10 +"
b10 *"
03"
0z
bx $
bx !
bx *
bx K
bx H
bx Q
bx W
bx F
bx N
bx X
bx g
bx 9
bx C
bx h
bx '
bx 6
bx !"
b100 x
b101 w
b1 0"
b101 /"
b101 7"
b1010000000000000000 %"
1_
#60
0_
#65
b1110000000000000000 a
bx =
bx E
bx >
bx ;
bx D
bx A
bx P
bx $"
0j
0k
14"
1|
1{
13"
1z
bx t
b1000 x
b1010 w
b110 ,"
b10 0"
b110 /"
b110 7"
1_
#70
0_
#75
b10000000000000000000 a
b10010010000000000000000 9
b10010010000000000000000 C
b10010010000000000000000 h
b10000100000000000000000 0
b10000100000000000000000 8
b100001000000000000000000000000000000000 1
b101100000000000000000 .
b101100000000000000000 7
b101100000000000000000 ,
b101100000000000000000 4
b101100000000000000000 d
b11100000000000000000 #
b11100000000000000000 +
b10000000000000000000 )
b10000000000000000000 #"
b111000000000000000000000000000000000 $
b1110000000000000000 !
b1110000000000000000 *
b1110000000000000000 '
b1110000000000000000 6
b1110000000000000000 !"
1k
b10 b
b1 6"
b1 +"
b1 *"
04"
03"
0|
0{
0z
b1 x
b101 w
b1010 ,"
b11 0"
b111 /"
b111 7"
b1110000000000000000 %"
1_
#80
0_
#85
b10011000000000000000000 9
b10011000000000000000000 C
b10011000000000000000000 h
b10001010000000000000000 0
b10001010000000000000000 8
b100010100000000000000000000000000000000 1
b101110000000000000000 .
b101110000000000000000 7
b101110000000000000000 ,
b101110000000000000000 4
b101110000000000000000 d
b10010000000000000000 )
b10010000000000000000 #"
b10010000000000000000 a
0k
13"
1z
b101100000000000000000 t
b10 x
b1010 w
b1001 ,"
b0 0"
b0 /"
b1000 7"
1_
#90
0_
#95
b10100000000000000000 a
b10110000000000000000000 =
b10110000000000000000000 E
bx 0
bx 8
b101100000000000000000000000000000000000 >
b101100000000000000000 ;
b101100000000000000000 D
b101100000000000000000 A
b101100000000000000000 P
b101100000000000000000 $"
bx )
bx #"
bx 1
bx .
bx 7
bx ,
bx 4
bx d
bx #
bx +
1j
1k
b1 b
b10 6"
b10 +"
b10 *"
03"
0z
bx $
bx !
bx *
bx 9
bx C
bx h
bx '
bx 6
bx !"
b100 x
b101 w
b101 ,"
b1 0"
b1 /"
b1001 7"
b10010000000000000000 %"
1_
#100
0_
#105
b10110000000000000000 a
bx =
bx E
bx >
bx ;
bx D
bx A
bx P
bx $"
0j
0k
14"
1|
1{
13"
1z
bx t
b1000 x
b1010 w
b110 ,"
b10 0"
b10 /"
b1010 7"
1_
#110
0_
#115
b11000000000000000000 a
b11100010000000000000000 9
b11100010000000000000000 C
b11100010000000000000000 h
b11001100000000000000000 0
b11001100000000000000000 8
b110011000000000000000000000000000000000 1
b1000100000000000000000 .
b1000100000000000000000 7
b1000100000000000000000 ,
b1000100000000000000000 4
b1000100000000000000000 d
b101100000000000000000 #
b101100000000000000000 +
b11000000000000000000 )
b11000000000000000000 #"
b1011000000000000000000000000000000000 $
b10110000000000000000 !
b10110000000000000000 *
b10110000000000000000 '
b10110000000000000000 6
b10110000000000000000 !"
1k
b10 b
b1 6"
b1 +"
b1 *"
04"
03"
0|
0{
0z
b1 x
b101 w
b1010 ,"
b11 0"
b11 /"
b1011 7"
b10110000000000000000 %"
1_
#120
0_
#125
b11101000000000000000000 9
b11101000000000000000000 C
b11101000000000000000000 h
b11010010000000000000000 0
b11010010000000000000000 8
b110100100000000000000000000000000000000 1
b1000110000000000000000 .
b1000110000000000000000 7
b1000110000000000000000 ,
b1000110000000000000000 4
b1000110000000000000000 d
b11010000000000000000 )
b11010000000000000000 #"
b11010000000000000000 a
0k
13"
1z
b1000100000000000000000 t
b10 x
b1010 w
b1001 ,"
b0 0"
b100 /"
b1100 7"
1_
#130
0_
#135
b11100000000000000000 a
b100010000000000000000000 =
b100010000000000000000000 E
bx 0
bx 8
b1000100000000000000000000000000000000000 >
b1000100000000000000000 ;
b1000100000000000000000 D
b1000100000000000000000 A
b1000100000000000000000 P
b1000100000000000000000 $"
bx )
bx #"
bx 1
bx .
bx 7
bx ,
bx 4
bx d
bx #
bx +
1j
1k
b1 b
b10 6"
b10 +"
b10 *"
03"
0z
bx $
bx !
bx *
bx 9
bx C
bx h
bx '
bx 6
bx !"
b100 x
b101 w
b101 ,"
b1 0"
b101 /"
b1101 7"
b11010000000000000000 %"
1_
#140
0_
#145
b11110000000000000000 a
bx =
bx E
bx >
bx ;
bx D
bx A
bx P
bx $"
0j
0k
14"
1|
1{
13"
1z
bx t
b1000 x
b1010 w
b110 ,"
b10 0"
b110 /"
b1110 7"
1_
#150
0_
#155
b100000000000000000000 a
1k
b10 b
b11 6"
b11 +"
b11 *"
04"
03"
0|
0{
0z
b1 x
b101 w
b1010 ,"
b11 0"
b111 /"
b1111 7"
b11110000000000000000 %"
1_
#160
0_
#165
b100010000000000000000 a
0k
15"
1~
1}
13"
1z
b10 x
b1010 w
b1011 ,"
b0 0"
b0 /"
12"
1_
#170
0_
#175
b100100000000000000000 a
1j
1k
b11 b
b10 6"
b10 +"
b10 *"
05"
03"
0~
0}
0z
b1 y
b100 x
b101 w
b1111 ,"
b1 0"
b1 /"
b100010000000000000000 %"
1_
#180
0_
#185
b100110000000000000000 a
0j
0k
14"
1|
1{
13"
1z
b10 y
b1000 x
b1010 w
b1110 ,"
b10 0"
b10 /"
1_
#190
0_
#195
b101000000000000000000 a
b110000010000000000000000 9
b110000010000000000000000 C
b110000010000000000000000 h
b101011100000000000000000 0
b101011100000000000000000 8
b1010111000000000000000000000000000000000 1
b1110100000000000000000 .
b1110100000000000000000 7
b1110100000000000000000 ,
b1110100000000000000000 4
b1110100000000000000000 d
b1001100000000000000000 #
b1001100000000000000000 +
b101000000000000000000 )
b101000000000000000000 #"
b10011000000000000000000000000000000000 $
b100110000000000000000 !
b100110000000000000000 *
b100110000000000000000 '
b100110000000000000000 6
b100110000000000000000 !"
1i
1k
b10 b
b1 6"
b1 +"
b1 *"
04"
03"
0|
0{
0z
b100 y
b1 x
b101 w
b1010 ,"
b11 0"
b11 /"
b100110000000000000000 %"
1_
#200
0_
#205
b110001000000000000000000 9
b110001000000000000000000 C
b110001000000000000000000 h
b101100010000000000000000 0
b101100010000000000000000 8
b1011000100000000000000000000000000000000 1
b1110110000000000000000 .
b1110110000000000000000 7
b1110110000000000000000 ,
b1110110000000000000000 4
b1110110000000000000000 d
b101010000000000000000 )
b101010000000000000000 #"
b101010000000000000000 a
0i
0k
13"
1z
b1110100000000000000000 v
b1110100000000000000000 t
b1000 y
b10 x
b1010 w
b1001 ,"
b0 0"
b100 /"
1_
#210
0_
#215
b101100000000000000000 a
b111010000000000000000000 =
b111010000000000000000000 E
bx 0
bx 8
b1110100000000000000000000000000000000000 >
b1110100000000000000000 ;
b1110100000000000000000 D
b1110100000000000000000 A
b1110100000000000000000 P
b1110100000000000000000 $"
bx )
bx #"
bx 1
bx .
bx 7
bx ,
bx 4
bx d
bx #
bx +
1j
1k
b1 b
b10 6"
b10 +"
b10 *"
03"
0z
bx $
bx !
bx *
bx 9
bx C
bx h
bx '
bx 6
bx !"
b0 y
b100 x
b101 w
b101 ,"
b1 0"
b101 /"
b101010000000000000000 %"
1_
#220
0_
#225
b101110000000000000000 a
bx =
bx E
bx >
bx ;
bx D
bx A
bx P
bx $"
0j
0k
14"
1|
1{
13"
1z
bx t
b1000 x
b1010 w
b110 ,"
b10 0"
b110 /"
1_
#230
0_
#235
b110000000000000000000 a
1k
b10 b
b11 6"
b11 +"
b11 *"
04"
03"
0|
0{
0z
b1 x
b101 w
b1010 ,"
b11 0"
b111 /"
b101110000000000000000 %"
1_
#240
0_
#245
b110010000000000000000 a
0k
15"
1~
1}
13"
1z
b10 x
b1010 w
b1011 ,"
b0 0"
b0 /"
1_
#250
0_
#255
b110100000000000000000 a
b111010000000000000000000 =
b111010000000000000000000 E
b1110100000000000000000000000000000000000 >
b1110100000000000000000 ;
b1110100000000000000000 D
b1110100000000000000000 A
b1110100000000000000000 P
b1110100000000000000000 $"
1j
1k
b11 b
b10 6"
b10 +"
b10 *"
05"
03"
0~
0}
0z
b1 y
b100 x
b101 w
b1111 ,"
b1 0"
b1 /"
b110010000000000000000 %"
1_
#260
0_
#265
b110110000000000000000 a
0j
0k
14"
1|
1{
13"
1z
b10 y
b1000 x
b1010 w
b1110 ,"
b10 0"
b10 /"
1_
#270
0_
#275
b111000000000000000000 a
b1000100010000000000000000 9
b1000100010000000000000000 C
b1000100010000000000000000 h
b111101100000000000000000 0
b111101100000000000000000 8
bx =
bx E
b1111011000000000000000000000000000000000 1
b10100100000000000000000 .
b10100100000000000000000 7
b10100100000000000000000 ,
b10100100000000000000000 4
b10100100000000000000000 d
b1101100000000000000000 #
b1101100000000000000000 +
bx >
bx ;
bx D
bx A
bx P
bx $"
b111000000000000000000 )
b111000000000000000000 #"
b11011000000000000000000000000000000000 $
b110110000000000000000 !
b110110000000000000000 *
b110110000000000000000 '
b110110000000000000000 6
b110110000000000000000 !"
1i
1k
b10 b
b1 6"
b1 +"
b1 *"
04"
03"
0|
0{
0z
b100 y
b1 x
b101 w
b1010 ,"
b11 0"
b11 /"
b110110000000000000000 %"
1_
#280
0_
#285
b1000101000000000000000000 9
b1000101000000000000000000 C
b1000101000000000000000000 h
b111110010000000000000000 0
b111110010000000000000000 8
b1111100100000000000000000000000000000000 1
b10100110000000000000000 .
b10100110000000000000000 7
b10100110000000000000000 ,
b10100110000000000000000 4
b10100110000000000000000 d
b111010000000000000000 )
b111010000000000000000 #"
b111010000000000000000 a
0i
0k
13"
1z
b10100100000000000000000 v
b10100100000000000000000 t
b1000 y
b10 x
b1010 w
b1001 ,"
b0 0"
b100 /"
1_
#290
0_
