src/fixed_mult.v
module z_fixed_mult(
    input clk,
    input [size-1:0] in0,
    input [size-1:0] in1,
    output reg [size-1:0] product
);
    parameter size = 32;
    reg [(size*2) - 1: 0] interm;

    assign interm = {{32{in0[31]}}, in0} * {{32{in1[31]}},in1};

    always @(posedge clk) begin
        product <= interm[2*size-1-(size/2):(size/2)];
    end


    initial begin
        $dumpfile("dump.vcd");
        $dumpvars(3, z_fixed_mult);
    end

endmodule

module fixed_mult(
    input [size-1:0] in0,
    input [size-1:0] in1,
    output [size-1:0] product
);
    parameter size = 32;
    reg [(size*2) - 1: 0] interm;

    assign interm = {{32{in0[31]}}, in0} * {{32{in1[31]}},in1};
    assign product = interm[2*size-1-(size/2):(size/2)];


    initial begin
        $dumpfile("dump.vcd");
        $dumpvars(3, fixed_mult);
    end

endmodule

src/MAC.v
//Delayed multiply and accumulate units
module z_mac(
    input clk,
    input [size-1:0] in0,
    input [size-1:0] in1,
    input [size-1:0] cons,
    input [size-1:0] in3,
    output reg [size-1:0] d
);
    parameter size = 32;

    wire [size-1:0] in;
    wire [size-1:0] temp;
    wire [size-1:0] mult;
    wire [size-1:0] sum0;

    assign sum0 = in0 + in1;

    fixed_mult m0(.in0(sum0), .in1(cons), .product(mult));

    //assign in = a + b;
    //assign temp = in * const;


    //assign d = ((in0+in1)*cons) + in3;
    //assign d = mult + in3;

    always@(posedge clk) begin
        d <= mult + in3;
    end

    initial begin
        $dumpfile("dump.vcd");
        $dumpvars(2, z_mac);
    end

endmodule

//Non-delayed multiply and accumulate units
module mac(
    input clk,
    input [size-1:0] in0,
    input [size-1:0] in1,
    input [size-1:0] cons,
    input [size-1:0] in3,
    output reg [size-1:0] d
);
    parameter size = 32;

    wire [size-1:0] in;
    wire [size-1:0] temp;
    wire [size-1:0] mult;
    wire [size-1:0] sum0;

    assign sum0 = in0 + in1;

    fixed_mult m0(.in0(sum0), .in1(cons), .product(mult));

    //assign in = a + b;
    //assign temp = in * const;


    //assign d = ((in0+in1)*cons) + in3;
    assign d = mult + in3;

    initial begin
        $dumpfile("dump.vcd");
        $dumpvars(2, mac);
    end

endmodule

src/transform.v
//Implementation of a one-dimensional recursive DAUB-4 DWT architecture

module transform (
    input clk,
    input resetn,
    input [size-1:0] x,
    output reg [size-1:0] L,
    output reg [size-1:0] H
    //Add register and delay unit enables to signal IO list
);

    //enable signals
    //reg EnR4;
    reg EnR3;
    reg EnR2;
    reg EnR1;
    reg EnD1a;
    reg EnD2a;
    reg EnD3a;
    //reg EnD4a;
    reg EnD1b;
    reg EnD2b;
    reg EnD3b;
    //reg EnD4b;
    reg EnD1c;
    reg EnD2c;
    reg EnD3c;
    //reg EnD4c;
    reg EnD1d;
    reg EnD2d;
    reg EnD3d;
    //reg EnD4d;
    reg EnR2p;
    reg EnR3p;
    //reg EnR4p;

    //Control switch signals
    reg [1:0] S1;
    reg [1:0] S2;
    reg [1:0] S3;
    reg [1:0] S4;
    reg [1:0] S5;
    reg [1:0] S6;
    reg S7;

    parameter size = 32;

    parameter alpha = 32'b11111111111111100100010010011000;
    parameter beta = 32'b00000000000000000110111011011010;
    parameter gamma = 32'b11111111111111111110111011011010;
    parameter lambda = 32'b00000000000000010000000000000000;
    //parameter delta = 5*(2**16);
    //parameter zeta = 6*(2**16);
    parameter omega = 32'b00000000000000011110111010001110;
    parameter nabla = 32'b00000000000000001000010010000100;

    //Enable signals

    //Even registers
    reg [size-1:0] R1;
    reg [size-1:0] R2;
    reg [size-1:0] R3;
    //reg [size-1:0] R4;

    //Odd registers
    reg [size-1:0] R2p;
    reg [size-1:0] R3p;
    //reg [size-1:0] R4p;

    //Delay units
    reg [size-1:0] D1a;
    reg [size-1:0] D2a;
    reg [size-1:0] D3a;
    //reg [size-1:0] D4a;

    reg [size-1:0] D1b;
    reg [size-1:0] D2b;
    reg [size-1:0] D3b;
    //reg [size-1:0] D4b;

    reg [size-1:0] D1c;
    reg [size-1:0] D2c;
    reg [size-1:0] D3c;
    //reg [size-1:0] D4c;

    reg [size-1:0] D1d;
    reg [size-1:0] D2d;
    reg [size-1:0] D3d;
    //reg [size-1:0] D4d;

    //shift registers
    reg [3:0] EnD1shift;
    reg [3:0] EnD2shift;
    reg [3:0] EnD3shift;
    reg [3:0] S3shift;

    reg [size-1: 0] Even0;
    reg [size-1: 0] Even1;
    reg [size-1: 0] Even2;
    reg [size-1: 0] Even3;
    reg [size-1: 0] Even4;
    reg [size-1: 0] Even5;

    reg [size-1: 0] Odd0;
    reg [size-1: 0] Odd1;
    reg [size-1: 0] Odd2;
    reg [size-1: 0] Odd3;
    reg [size-1: 0] Odd4;
    reg [size-1: 0] Odd5;

    //feedback unit
    reg [size-1:0] y;
    //reg [size-1:0] L;

    //Just for Daub4
    assign EnD1a = EnD1shift[2];
    assign EnD2a = EnD2shift[2];
    assign EnD3a = EnD3shift[2];
    assign S3 = S3shift[3:2];

    always@(*) begin

        //DAUB-4 DWT Muxes
        //Latch?
        case(S1)
        2'b11:Even0 = R3;
        2'b10: Even0 = R2;
        2'b01: Even0 = R1;
        2'b00: Even0 = 32'bx;
        endcase

        case(S2)
        2'b11:Odd0 = R3p;
        2'b10: Odd0 = R2p;
        2'b01: Odd0 = x;
        2'b00: Odd0 = 32'bx;
        endcase

        case(S3)
        2'b11:Odd3 = D3a;
        2'b10: Odd3 = D2a;
        2'b01: Odd3 = D1a;
        endcase     

        //if (S4) y<= Even5;
        //else L<= Even5;
        y <= Even5; //verify timing
        L <= Even5; 

    end

    always@(posedge clk) begin
        Even1 <= Even0;
        Even3 <= Even2;
        Odd2 <= Odd1;

        if (EnR1) R1 <= x;
        if (EnR2) R2 <= y;
        if (EnR3) R3 <= y;
        //if (EnR4) R4 <= y;

        //if (EnR2p) R2p <= y;
        R2p <= y;
        if (EnR3p) R3p <= y;
        //if (EnR4p) R4p <= y;


        if (EnD1a) D1a <= Odd2;
        if (EnD2a) D2a <= Odd2;
        if (EnD3a) D3a <= Odd2;

    end

    //Multiply and accumulate units for Daub-4 DWT
    z_mac u0(.clk(clk), .in0(Even0), .in1(0), .in3(Odd0), .d(Odd1), .cons(alpha));
    z_mac u1(.clk(clk),.in0(Odd1), .in1(0), .in3(Even1), .d(Even2), .cons(beta));
    mac u2(.clk(clk),.in0(Odd3), .in1(0), .in3(Even3), .d(Even4), .cons(gamma));
    mac u3(.clk(clk),.in0(Even4), .in1(0), .in3(Odd3), .d(Odd4), .cons(lambda));

    z_fixed_mult m1(.clk(clk), .in0(Even4), .in1(omega), .product(Even5));
    z_fixed_mult m2(.clk(clk),.in0(Odd4), .in1(nabla), .product(H));

    //control unit
    reg [3:0] state;
    reg [2:0] cycle1;
    reg [1:0] cycle2;
    reg cycle2En;
    reg finalEn;
    reg SEn;
    reg DshiftEn;

    reg preEnD1a;
    reg preEnD2a;
    reg preEnD3a;

    reg [1:0] preS3;

    //enable signals, might need to extend the range for switch logic
    always@(*) begin
        EnR1 = 1'b0;
        EnR2 = 1'b0;
        EnR3 = 1'b0;
        //EnR2p = 1'b0;
        EnR3p = 1'b0;
        S1 = 2'b0;
        S2 = 2'b0;
        //S3 = 2'b0;
        //S4 = 2'b0;
        //S5 = 2'b0;
        //S6 = 2'b0;
        //S7 = 1'b0;
        SEn = 1'b0;
        preEnD1a = 1'b0;
        preEnD2a = 1'b0;
        preEnD3a = 1'b0;
        //preS3 = 2'b0;
        //EnD1a = 1'b0;

        if (!cycle1[0]) begin //checking 2k cycle
            EnR1 = 1'b1;
            preEnD1a = 1'b1;
        end

        if (cycle1[0]) begin//checking 2k+1 cycle
            S1 = 2'b01;
            S2 = 2'b01;
            preS3 = 2'b01;
        end

        if (cycle1[1] & cycle1[0]) begin //4k+4 cycle
            EnR2 = 1'b1; 
            //EnR2p = 1'b1; 
            preEnD2a = 1'b1;
        end

        if ((cycle2[0] & !cycle2[1])) begin  //4k+6 cycle
            S1 = 2'b10;
            S2 = 2'b10;
            preS3 = 2'b10;
        end

        if ((!cycle1[2] & !cycle1[1] & !cycle1[0]) & (state[3] & (state[0]))) begin //8k+9 cycle
            EnR3 = 1'b1;
            EnR3p = 1'b1;
            preEnD3a = 1'b1;
        end

        if ((state[0] & state[1] & state[2] & state[3]) & (cycle1[2] & cycle1[1] & cycle1[0])) begin //8k+16 cycle
            S1 = 2'b11;
            S2 = 2'b11;
            preS3 = 2'b11;
        end

        

    end

    //counter
    always@(posedge clk) begin
        if (!resetn) begin
            state <= 0;
            cycle1 <= 0;
            cycle2 <= 0;
            cycle2En <= 0;
            finalEn <= 0;


        end
        else begin
            if (state == 4'b1111) begin
                state <= 4'b1111; //counts to 25
                finalEn <= 1;
            end
            else state <= state + 1;

            if (cycle1 == 3'b111) cycle1 <= 0;
            else cycle1 <= cycle1 + 1;

            if (state[1] & state[0]) cycle2En <= 1;

            if (cycle2En) cycle2 <= cycle2 + 1;

            S3shift <= {S3shift[1:0], preS3};

            EnD1shift <= {EnD1shift[3:0], preEnD1a};
            EnD2shift <= {EnD2shift[3:0], preEnD2a};
            EnD3shift <= {EnD3shift[3:0], preEnD3a};
        
        end
    end
    

    initial begin
        $dumpfile("dump.vcd");
        $dumpvars(1, transform);
    end


endmodule

verif/dump.vcd
$date
	Fri Oct 25 21:39:07 2024
$end
$version
	Icarus Verilog
$end
$timescale
	1ps
$end
$scope module transform $end
$scope module u0 $end
$scope module m0 $end
$var wire 32 ! in0 [31:0] $end
$var wire 32 " in1 [31:0] $end
$var wire 32 # product [31:0] $end
$var wire 64 $ interm [63:0] $end
$var parameter 32 % size $end
$upscope $end
$upscope $end
$upscope $end
$scope module transform $end
$scope module u0 $end
$var wire 1 & clk $end
$var wire 32 ' cons [31:0] $end
$var wire 32 ( in0 [31:0] $end
$var wire 32 ) in1 [31:0] $end
$var wire 32 * in3 [31:0] $end
$var wire 32 + sum0 [31:0] $end
$var wire 32 , mult [31:0] $end
$var parameter 32 - size $end
$var reg 32 . d [31:0] $end
$scope module m0 $end
$upscope $end
$upscope $end
$upscope $end
$scope module transform $end
$scope module u1 $end
$scope module m0 $end
$var wire 32 / in0 [31:0] $end
$var wire 32 0 in1 [31:0] $end
$var wire 32 1 product [31:0] $end
$var wire 64 2 interm [63:0] $end
$var parameter 32 3 size $end
$upscope $end
$upscope $end
$upscope $end
$scope module transform $end
$scope module u1 $end
$var wire 1 & clk $end
$var wire 32 4 cons [31:0] $end
$var wire 32 5 in0 [31:0] $end
$var wire 32 6 in1 [31:0] $end
$var wire 32 7 in3 [31:0] $end
$var wire 32 8 sum0 [31:0] $end
$var wire 32 9 mult [31:0] $end
$var parameter 32 : size $end
$var reg 32 ; d [31:0] $end
$scope module m0 $end
$upscope $end
$upscope $end
$upscope $end
$scope module transform $end
$scope module u2 $end
$scope module m0 $end
$var wire 32 < in0 [31:0] $end
$var wire 32 = in1 [31:0] $end
$var wire 32 > product [31:0] $end
$var wire 64 ? interm [63:0] $end
$var parameter 32 @ size $end
$upscope $end
$upscope $end
$upscope $end
$scope module transform $end
$scope module u2 $end
$var wire 1 & clk $end
$var wire 32 A cons [31:0] $end
$var wire 32 B in0 [31:0] $end
$var wire 32 C in1 [31:0] $end
$var wire 32 D in3 [31:0] $end
$var wire 32 E sum0 [31:0] $end
$var wire 32 F mult [31:0] $end
$var wire 32 G d [31:0] $end
$var parameter 32 H size $end
$scope module m0 $end
$upscope $end
$upscope $end
$upscope $end
$scope module transform $end
$scope module u3 $end
$scope module m0 $end
$var wire 32 I in0 [31:0] $end
$var wire 32 J in1 [31:0] $end
$var wire 32 K product [31:0] $end
$var wire 64 L interm [63:0] $end
$var parameter 32 M size $end
$upscope $end
$upscope $end
$upscope $end
$scope module transform $end
$scope module u3 $end
$var wire 1 & clk $end
$var wire 32 N cons [31:0] $end
$var wire 32 O in0 [31:0] $end
$var wire 32 P in1 [31:0] $end
$var wire 32 Q in3 [31:0] $end
$var wire 32 R sum0 [31:0] $end
$var wire 32 S mult [31:0] $end
$var wire 32 T d [31:0] $end
$var parameter 32 U size $end
$scope module m0 $end
$upscope $end
$upscope $end
$upscope $end
$scope module transform $end
$scope module m1 $end
$var wire 1 & clk $end
$var wire 32 V in1 [31:0] $end
$var wire 64 W interm [63:0] $end
$var wire 32 X in0 [31:0] $end
$var parameter 32 Y size $end
$var reg 32 Z product [31:0] $end
$upscope $end
$upscope $end
$scope module transform $end
$scope module m2 $end
$var wire 1 & clk $end
$var wire 32 [ in1 [31:0] $end
$var wire 64 \ interm [63:0] $end
$var wire 32 ] in0 [31:0] $end
$var parameter 32 ^ size $end
$var reg 32 _ product [31:0] $end
$upscope $end
$upscope $end
$scope module transform $end
$var wire 1 & clk $end
$var wire 1 ` resetn $end
$var wire 32 a x [31:0] $end
$var wire 2 b S3 [1:0] $end
$var wire 32 c Odd4 [31:0] $end
$var wire 32 d Odd1 [31:0] $end
$var wire 32 e H [31:0] $end
$var wire 32 f Even5 [31:0] $end
$var wire 32 g Even4 [31:0] $end
$var wire 32 h Even2 [31:0] $end
$var wire 1 i EnD3a $end
$var wire 1 j EnD2a $end
$var wire 1 k EnD1a $end
$var parameter 32 l alpha $end
$var parameter 32 m beta $end
$var parameter 32 n gamma $end
$var parameter 32 o lambda $end
$var parameter 32 p nabla $end
$var parameter 32 q omega $end
$var parameter 32 r size $end
$var reg 32 s D1a [31:0] $end
$var reg 32 t D2a [31:0] $end
$var reg 32 u D3a [31:0] $end
$var reg 4 v EnD1shift [3:0] $end
$var reg 4 w EnD2shift [3:0] $end
$var reg 4 x EnD3shift [3:0] $end
$var reg 1 y EnR1 $end
$var reg 1 z EnR2 $end
$var reg 1 { EnR3 $end
$var reg 1 | EnR3p $end
$var reg 32 } Even0 [31:0] $end
$var reg 32 ~ Even1 [31:0] $end
$var reg 32 !" Even3 [31:0] $end
$var reg 32 "" L [31:0] $end
$var reg 32 #" Odd0 [31:0] $end
$var reg 32 $" Odd2 [31:0] $end
$var reg 32 %" Odd3 [31:0] $end
$var reg 32 &" R1 [31:0] $end
$var reg 32 '" R2 [31:0] $end
$var reg 32 (" R2p [31:0] $end
$var reg 32 )" R3 [31:0] $end
$var reg 32 *" R3p [31:0] $end
$var reg 2 +" S1 [1:0] $end
$var reg 2 ," S2 [1:0] $end
$var reg 4 -" S3shift [3:0] $end
$var reg 1 ." SEn $end
$var reg 3 /" cycle1 [2:0] $end
$var reg 2 0" cycle2 [1:0] $end
$var reg 1 1" cycle2En $end
$var reg 1 2" finalEn $end
$var reg 1 3" preEnD1a $end
$var reg 1 4" preEnD2a $end
$var reg 1 5" preEnD3a $end
$var reg 2 6" preS3 [1:0] $end
$var reg 4 7" state [3:0] $end
$var reg 32 8" y [31:0] $end
$upscope $end
$enddefinitions $end
$comment Show the parameter values. $end
$dumpall
b100000 r
b11110111010001110 q
b1000010010000100 p
b10000000000000000 o
b11111111111111111110111011011010 n
b110111011011010 m
b11111111111111100100010010011000 l
b100000 ^
b100000 Y
b100000 U
b100000 M
b100000 H
b100000 @
b100000 :
b100000 3
b100000 -
b100000 %
$end
#0
$dumpvars
bx 8"
bx 7"
bx 6"
x5"
x4"
x3"
x2"
x1"
bx 0"
bx /"
x."
bx -"
bx ,"
bx +"
bx *"
bx )"
bx ("
bx '"
bx &"
bx %"
bx $"
bx #"
bx ""
bx !"
bx ~
bx }
x|
x{
xz
xy
bx x
bx w
bx v
bx u
bx t
bx s
xk
xj
xi
bx h
bx g
bx f
bx e
bx d
bx c
bx b
bz a
0`
bx _
bx ]
bx \
b1000010010000100 [
bx Z
bx X
bx W
b11110111010001110 V
bx T
bx S
bx R
bx Q
b0 P
bx O
b10000000000000000 N
bx L
bx K
b10000000000000000 J
bx I
bx G
bx F
bx E
bx D
b0 C
bx B
b11111111111111111110111011011010 A
bx ?
bx >
b11111111111111111110111011011010 =
bx <
bx ;
bx 9
bx 8
bx 7
b0 6
bx 5
b110111011011010 4
bx 2
bx 1
b110111011011010 0
bx /
bx .
bx ,
bx +
bx *
b0 )
bx (
b11111111111111100100010010011000 '
0&
bx $
bx #
b11111111111111100100010010011000 "
bx !
$end
#5
b10000000000000000 a
1`
05"
04"
13"
0."
b0 ,"
b0 +"
0|
0{
0z
1y
02"
01"
b0 0"
b0 /"
b0 7"
1&
#10
0&
#15
b100000000000000000 a
b11111111111111100100010010011000 #
b11111111111111100100010010011000 ,
b1111111111111111111111111111111001000100100110000000000000000000 $
b100000000000000000 *
b100000000000000000 #"
b10000000000000000 !
b10000000000000000 +
b10000000000000000 (
b10000000000000000 }
b1 6"
b1 ,"
b1 +"
03"
0y
bx0 x
bx0 w
bx1 v
b1 /"
b1 7"
b10000000000000000 &"
1&
#20
0&
#25
b10000000000000000 a
bx #
bx ,
b1110110110011 1
b1110110110011 9
bx *
bx #"
bx $
bx !
bx +
bx (
bx }
b11101101100111011100101110000 2
13"
1y
b0 ,"
b0 +"
b100010010011000 /
b100010010011000 8
b100010010011000 .
b100010010011000 5
b100010010011000 d
b10000000000000000 7
b10000000000000000 ~
bx00 x
bx00 w
bx10 v
bx01 -"
b10 /"
b10 7"
1&
#30
0&
#35
b100000000000000000 a
b11111111111111100100010010011000 #
b11111111111111100100010010011000 ,
b1111111111111111111111111111111001000100100110000000000000000000 $
b100000000000000000 *
b100000000000000000 #"
b10000000000000000 !
b10000000000000000 +
b10000000000000000 (
b10000000000000000 }
0i
0j
1k
b1 b
14"
1z
b1 ,"
b1 +"
03"
0y
bx 1
bx 9
bx000 x
bx000 w
bx101 v
b101 -"
b11 /"
b11 7"
b100010010011000 $"
bx 7
bx ~
b10001110110110011 ;
b10001110110110011 h
bx 2
bx /
bx 8
bx .
bx 5
bx d
1&
#40
0&
#45
b10000000000000000 a
b10110101000001000001011111001000 \
b10101110110110010 T
b10101110110110010 ]
b10101110110110010 c
b10001100100011010 K
b10001100100011010 S
b100011001000110100000000000000000 L
b1000011111000011000001100001101100 W
b10001100100011010 I
b10001100100011010 R
b10001100100011010 G
b10001100100011010 O
b10001100100011010 X
b10001100100011010 g
b11111111111111111111101101100111 >
b11111111111111111111101101100111 F
b1110110110011 1
b1110110110011 9
b1111111111111111111111111111111111111011011001111011100101110000 ?
bx #
bx ,
b11101101100111011100101110000 2
b100010010011000 <
b100010010011000 E
b100010010011000 B
b100010010011000 Q
b100010010011000 %"
bx *
bx #"
bx $
bx !
bx +
bx (
bx }
0k
13"
1y
04"
b0 ,"
b0 +"
0z
b100010010011000 /
b100010010011000 8
b100010010011000 .
b100010010011000 5
b100010010011000 d
bx ;
bx h
b100010010011000 s
bx $"
b10001110110110011 D
b10001110110110011 !"
b10000000000000000 7
b10000000000000000 ~
b0 x
b1 w
b1010 v
11"
b100 /"
b100 7"
1&
#50
0&
#55
b100000000000000000 a
b100001111100001100 ""
b100001111100001100 8"
1k
b10 6"
b10 ,"
b10 +"
03"
0y
bx \
bx T
bx ]
bx c
bx K
bx S
bx 1
bx 9
b10 w
b101 v
b1 0"
b101 /"
b101 7"
b100010010011000 $"
bx L
bx I
bx R
bx W
bx G
bx O
bx X
bx g
bx D
bx !"
bx 7
bx ~
b1011010100000100 _
b1011010100000100 e
b100001111100001100 Z
b100001111100001100 f
b10001110110110011 ;
b10001110110110011 h
bx 2
bx /
bx 8
bx .
bx 5
bx d
1&
#60
0&
#65
b10000000000000000 a
bx ""
bx 8"
b10110101000001000001011111001000 \
b10101110110110010 T
b10101110110110010 ]
b10101110110110010 c
b10001100100011010 K
b10001100100011010 S
b100011001000110100000000000000000 L
b1000011111000011000001100001101100 W
1j
0k
13"
1y
b0 ,"
b0 +"
bx ;
bx h
bx Z
bx f
bx _
bx e
b100001111100001100 ("
bx $"
b10001100100011010 I
b10001100100011010 R
b10001100100011010 G
b10001100100011010 O
b10001100100011010 X
b10001100100011010 g
b10001110110110011 D
b10001110110110011 !"
b100 w
b1010 v
b110 -"
b10 0"
b110 /"
b110 7"
1&
#70
0&
#75
b100000000000000000 a
b100001111100001100 ""
b100001111100001100 8"
b11111111111111100100010010011000 #
b11111111111111100100010010011000 ,
bx >
bx F
b1111111111111111111111111111111001000100100110000000000000000000 $
bx ?
bx <
bx E
bx B
bx Q
bx %"
b100000000000000000 *
b100000000000000000 #"
b10000000000000000 !
b10000000000000000 +
b10000000000000000 (
b10000000000000000 }
0j
1k
b10 b
14"
1z
b1 6"
b1 ,"
b1 +"
03"
0y
bx \
bx T
bx ]
bx c
bx K
bx S
b1000 w
b101 v
b1010 -"
b11 0"
b111 /"
b111 7"
bx ("
bx L
bx I
bx R
bx W
bx G
bx O
bx X
bx g
bx D
bx !"
b1011010100000100 _
b1011010100000100 e
b100001111100001100 Z
b100001111100001100 f
1&
#80
0&
#85
b10000000000000000 a
bx ""
bx 8"
b1110110110011 1
b1110110110011 9
bx #
bx ,
b11101101100111011100101110000 2
bx *
bx #"
bx $
bx !
bx +
bx (
bx }
0k
13"
1y
04"
b0 ,"
b0 +"
0z
b100010010011000 /
b100010010011000 8
b100010010011000 .
b100010010011000 5
b100010010011000 d
bx Z
bx f
bx _
bx e
bx s
b100001111100001100 ("
b100001111100001100 '"
b10000000000000000 7
b10000000000000000 ~
b1 w
b1010 v
b1001 -"
b0 0"
b0 /"
b1000 7"
1&
#90
0&
#95
b100000000000000000 a
b11111111111111000101001101101001 #
b11111111111111000101001101101001 ,
b1111111111111111111111111111110001010011011010011001111100100000 $
b100001111100001100 !
b100001111100001100 +
b100001111100001100 (
b100001111100001100 }
1k
b1 b
b10 6"
b10 ,"
b10 +"
03"
0y
bx 1
bx 9
b10 w
b101 v
b101 -"
b1 0"
b1 /"
b1001 7"
bx ("
b100010010011000 $"
bx 7
bx ~
b10001110110110011 ;
b10001110110110011 h
bx 2
bx /
bx 8
bx .
bx 5
bx d
1&
#100
0&
#105
b10000000000000000 a
b10110101000001000001011111001000 \
b10101110110110010 T
b10101110110110010 ]
b10101110110110010 c
b10001100100011010 K
b10001100100011010 S
b100011001000110100000000000000000 L
b1000011111000011000001100001101100 W
b10001100100011010 I
b10001100100011010 R
b10001100100011010 G
b10001100100011010 O
b10001100100011010 X
b10001100100011010 g
b11111111111111111111101101100111 >
b11111111111111111111101101100111 F
b1111111111111111111111111111111111111011011001111011100101110000 ?
bx #
bx ,
b100010010011000 <
b100010010011000 E
b100010010011000 B
b100010010011000 Q
b100010010011000 %"
bx $
bx !
bx +
bx (
bx }
1j
0k
13"
1y
b0 ,"
b0 +"
bx ;
bx h
b100010010011000 s
bx $"
b10001110110110011 D
b10001110110110011 !"
b100001111100001100 7
b100001111100001100 ~
b100 w
b1010 v
b110 -"
b10 0"
b10 /"
b1010 7"
1&
#110
0&
#115
b100000000000000000 a
b100001111100001100 ""
b100001111100001100 8"
b11111111111111100100010010011000 #
b11111111111111100100010010011000 ,
bx >
bx F
b1111111111111111111111111111111001000100100110000000000000000000 $
bx ?
bx <
bx E
bx B
bx Q
bx %"
b100000000000000000 *
b100000000000000000 #"
b10000000000000000 !
b10000000000000000 +
b10000000000000000 (
b10000000000000000 }
0j
1k
b10 b
14"
1z
b1 6"
b1 ,"
b1 +"
03"
0y
bx \
bx T
bx ]
bx c
bx K
bx S
b1000 w
b101 v
b1010 -"
b11 0"
b11 /"
b1011 7"
bx L
bx I
bx R
bx W
bx G
bx O
bx X
bx g
bx D
bx !"
bx 7
bx ~
b1011010100000100 _
b1011010100000100 e
b100001111100001100 Z
b100001111100001100 f
1&
#120
0&
#125
b10000000000000000 a
bx ""
bx 8"
b1110110110011 1
b1110110110011 9
bx #
bx ,
b11101101100111011100101110000 2
bx *
bx #"
bx $
bx !
bx +
bx (
bx }
0k
13"
1y
04"
b0 ,"
b0 +"
0z
b100010010011000 /
b100010010011000 8
b100010010011000 .
b100010010011000 5
b100010010011000 d
bx Z
bx f
bx _
bx e
bx s
b100001111100001100 ("
b10000000000000000 7
b10000000000000000 ~
b1 w
b1010 v
b1001 -"
b0 0"
b100 /"
b1100 7"
1&
#130
0&
#135
b100000000000000000 a
b11111111111111000101001101101001 #
b11111111111111000101001101101001 ,
b1111111111111111111111111111110001010011011010011001111100100000 $
b100001111100001100 !
b100001111100001100 +
b100001111100001100 (
b100001111100001100 }
1k
b1 b
b10 6"
b10 ,"
b10 +"
03"
0y
bx 1
bx 9
b10 w
b101 v
b101 -"
b1 0"
b101 /"
b1101 7"
bx ("
b100010010011000 $"
bx 7
bx ~
b10001110110110011 ;
b10001110110110011 h
bx 2
bx /
bx 8
bx .
bx 5
bx d
1&
#140
0&
#145
b10000000000000000 a
b10110101000001000001011111001000 \
b10101110110110010 T
b10101110110110010 ]
b10101110110110010 c
b10001100100011010 K
b10001100100011010 S
b100011001000110100000000000000000 L
b1000011111000011000001100001101100 W
b10001100100011010 I
b10001100100011010 R
b10001100100011010 G
b10001100100011010 O
b10001100100011010 X
b10001100100011010 g
b11111111111111111111101101100111 >
b11111111111111111111101101100111 F
b1111111111111111111111111111111111111011011001111011100101110000 ?
bx #
bx ,
b100010010011000 <
b100010010011000 E
b100010010011000 B
b100010010011000 Q
b100010010011000 %"
bx $
bx !
bx +
bx (
bx }
1j
0k
13"
1y
b0 ,"
b0 +"
bx ;
bx h
b100010010011000 s
bx $"
b10001110110110011 D
b10001110110110011 !"
b100001111100001100 7
b100001111100001100 ~
b100 w
b1010 v
b110 -"
b10 0"
b110 /"
b1110 7"
1&
#150
0&
#155
b100000000000000000 a
b100001111100001100 ""
b100001111100001100 8"
bx >
bx F
bx ?
bx <
bx E
bx B
bx Q
bx %"
0j
1k
b10 b
14"
1z
b11 6"
b11 ,"
b11 +"
03"
0y
bx \
bx T
bx ]
bx c
bx K
bx S
b1000 w
b101 v
b1010 -"
b11 0"
b111 /"
b1111 7"
bx L
bx I
bx R
bx W
bx G
bx O
bx X
bx g
bx D
bx !"
bx 7
bx ~
b1011010100000100 _
b1011010100000100 e
b100001111100001100 Z
b100001111100001100 f
1&
#160
0&
#165
b10000000000000000 a
bx ""
bx 8"
0k
15"
1|
1{
13"
1y
04"
b0 ,"
b0 +"
0z
bx Z
bx f
bx _
bx e
bx s
b100001111100001100 ("
b1 w
b1010 v
b1011 -"
b0 0"
b0 /"
12"
1&
#170
0&
#175
b100000000000000000 a
b11111111111111000101001101101001 #
b11111111111111000101001101101001 ,
b1111111111111111111111111111110001010011011010011001111100100000 $
b100001111100001100 !
b100001111100001100 +
b100001111100001100 (
b100001111100001100 }
1k
b11 b
b10 6"
b10 ,"
b10 +"
05"
03"
0|
0{
0y
b1 x
b10 w
b101 v
b1111 -"
b1 0"
b1 /"
bx ("
1&
#180
0&
#185
b10000000000000000 a
bx #
bx ,
bx $
bx !
bx +
bx (
bx }
1j
0k
13"
1y
b0 ,"
b0 +"
b100001111100001100 7
b100001111100001100 ~
b10 x
b100 w
b1010 v
b1110 -"
b10 0"
b10 /"
1&
#190
0&
#195
b100000000000000000 a
b11111111111111100100010010011000 #
b11111111111111100100010010011000 ,
b1111111111111111111111111111111001000100100110000000000000000000 $
b100000000000000000 *
b100000000000000000 #"
b10000000000000000 !
b10000000000000000 +
b10000000000000000 (
b10000000000000000 }
1i
0j
1k
b10 b
14"
1z
b1 6"
b1 ,"
b1 +"
03"
0y
b100 x
b1000 w
b101 v
b1010 -"
b11 0"
b11 /"
bx 7
bx ~
1&
#200
0&
#205
b10000000000000000 a
b1110110110011 1
b1110110110011 9
bx #
bx ,
b11101101100111011100101110000 2
bx *
bx #"
bx $
bx !
bx +
bx (
bx }
0i
0k
13"
1y
04"
b0 ,"
b0 +"
0z
b100010010011000 /
b100010010011000 8
b100010010011000 .
b100010010011000 5
b100010010011000 d
bx '"
b10000000000000000 7
b10000000000000000 ~
b1000 x
b1 w
b1010 v
b1001 -"
b0 0"
b100 /"
1&
#210
0&
#215
b100000000000000000 a
1k
b1 b
b10 6"
b10 ,"
b10 +"
03"
0y
bx 1
bx 9
b0 x
b10 w
b101 v
b101 -"
b1 0"
b101 /"
b100010010011000 $"
bx 7
bx ~
b10001110110110011 ;
b10001110110110011 h
bx 2
bx /
bx 8
bx .
bx 5
bx d
1&
#220
0&
#225
b10000000000000000 a
b10110101000001000001011111001000 \
b10101110110110010 T
b10101110110110010 ]
b10101110110110010 c
b10001100100011010 K
b10001100100011010 S
b100011001000110100000000000000000 L
b1000011111000011000001100001101100 W
b10001100100011010 I
b10001100100011010 R
b10001100100011010 G
b10001100100011010 O
b10001100100011010 X
b10001100100011010 g
b11111111111111111111101101100111 >
b11111111111111111111101101100111 F
b1111111111111111111111111111111111111011011001111011100101110000 ?
b100010010011000 <
b100010010011000 E
b100010010011000 B
b100010010011000 Q
b100010010011000 %"
1j
0k
13"
1y
b0 ,"
b0 +"
bx ;
bx h
b100010010011000 s
bx $"
b10001110110110011 D
b10001110110110011 !"
b100 w
b1010 v
b110 -"
b10 0"
b110 /"
1&
#230
0&
#235
b100000000000000000 a
b100001111100001100 ""
b100001111100001100 8"
bx >
bx F
bx ?
bx <
bx E
bx B
bx Q
bx %"
0j
1k
b10 b
14"
1z
b11 6"
b11 ,"
b11 +"
03"
0y
bx \
bx T
bx ]
bx c
bx K
bx S
b1000 w
b101 v
b1010 -"
b11 0"
b111 /"
bx L
bx I
bx R
bx W
bx G
bx O
bx X
bx g
bx D
bx !"
b1011010100000100 _
b1011010100000100 e
b100001111100001100 Z
b100001111100001100 f
1&
#240
0&
#245
b10000000000000000 a
bx ""
bx 8"
0k
15"
1|
1{
13"
1y
04"
b0 ,"
b0 +"
0z
bx Z
bx f
bx _
bx e
bx s
b100001111100001100 ("
b100001111100001100 '"
b1 w
b1010 v
b1011 -"
b0 0"
b0 /"
1&
#250
0&
